setup.py
jekyll_import_tistory/__init__.py
jekyll_import_tistory/data.py
jekyll_import_tistory/main.py
jekyll_import_tistory.egg-info/.DS_Store
jekyll_import_tistory.egg-info/PKG-INFO
jekyll_import_tistory.egg-info/SOURCES.txt
jekyll_import_tistory.egg-info/dependency_links.txt
jekyll_import_tistory.egg-info/entry_points.txt
jekyll_import_tistory.egg-info/not-zip-safe
jekyll_import_tistory.egg-info/requires.txt
jekyll_import_tistory.egg-info/top_level.txt