Metadata-Version: 1.0
Name: jekyll-import-tistory
Version: 0.0.1
Summary: produce jekyll post from tistory backup.xml
Home-page: http://github.com/rino0601/jekyll_import_tistory
Author: rino0601
Author-email: rino0601.dev@gmail.com
License: MIT
Platform: UNKNOWN
